{"livros":[{"autor":"Marco Aurélio","titulo":"Meditações","genero":"Filosofia","exemplares":4,"exemplaresAlugados":0},{"autor":"Jane Austen","titulo":"Orgulho e Preconceito","genero":"Romance","exemplares":4,"exemplaresAlugados":0},{"autor":"David Goggins","titulo":"Nada Pode Me Ferir","genero":"Autoajuda","exemplares":2,"exemplaresAlugados":0},{"autor":"H.G. Wells","titulo":"O Homem Invisível","genero":"Ficção Científica","exemplares":1,"exemplaresAlugados":0},{"autor":"Thomas More","titulo":"Utopia","genero":"Filosofia","exemplares":13,"exemplaresAlugados":1},{"autor":"George Orwell","titulo":"A Revolução dos Bichos","genero":"Fábula Política","exemplares":1,"exemplaresAlugados":0},{"autor":"C.S. Lewis","titulo":"As Crônicas de Nárnia","genero":"Fantasia","exemplares":8,"exemplaresAlugados":0},{"autor":"Tomás Antônio Gonzaga","titulo":"Cartas Chilenas","genero":"Sátira","exemplares":3,"exemplaresAlugados":0},{"autor":"Nicolau Maquiavel","titulo":"O Príncipe","genero":"Filosofia Política","exemplares":1,"exemplaresAlugados":0},{"autor":"Douglas Adams","titulo":"O Guia do Mochileiro das Galáxias","genero":"Ficção Científica","exemplares":10,"exemplaresAlugados":0}]}